password_manager/__init__.py
password_manager/vault.py
pwm/__init__.py
pwm/vault.py
pypwm-0.2.1.dist-info/METADATA
pypwm-0.2.1.dist-info/RECORD
pypwm-0.2.1.dist-info/WHEEL
pypwm-0.2.1.dist-info/top_level.txt
