Metadata-Version: 2.1
Name: pypwm
Version: 0.2.1
Summary: A library for password manager for Python
Home-page: https://github.com/patarapolw/pwm
Author: Pacharapol Withayasakpunt
Author-email: patarapolw@gmail.com
License: MIT
Keywords: password password-manager
Platform: UNKNOWN
Classifier: Development Status :: 4 - Beta
Classifier: Environment :: Console
Classifier: Intended Audience :: Developers
Classifier: Intended Audience :: System Administrators
Classifier: License :: OSI Approved :: MIT License
Classifier: Operating System :: OS Independent
Classifier: Programming Language :: Python :: 3.6
Classifier: Topic :: Security
Classifier: Topic :: Security :: Cryptography
Provides-Extra: tests
Requires-Dist: pycryptodome
Provides-Extra: tests
Requires-Dist: pytest; extra == 'tests'
Requires-Dist: pytest-readme; extra == 'tests'
